Metadata-Version: 1.0
Name: fipy-tools
Version: 0.1.0
Summary: Functional/Iteration Python tools for every module
Home-page: https://github.com/vaer-k/fipy
Author: vaer-k
Author-email: vincent@vaer-k.net
License: MIT
Platform: UNKNOWN
